{
 "kills_total":{
  "0":17,
  "1":25,
  "2":17,
  "3":18,
  "4":25,
  "5":19,
  "6":12,
  "7":16,
  "8":26,
  "9":26
 },
 "deaths_total":{
  "0":18,
  "1":20,
  "2":17,
  "3":17,
  "4":22,
  "5":21,
  "6":23,
  "7":21,
  "8":25,
  "9":17
 },
 "headshot_kills_total":{
  "0":8,
  "1":12,
  "2":12,
  "3":11,
  "4":13,
  "5":7,
  "6":5,
  "7":11,
  "8":13,
  "9":14
 },
 "ace_rounds_total":{
  "0":0,
  "1":0,
  "2":0,
  "3":0,
  "4":0,
  "5":0,
  "6":0,
  "7":0,
  "8":0,
  "9":0
 },
 "4k_rounds_total":{
  "0":0,
  "1":1,
  "2":0,
  "3":0,
  "4":1,
  "5":0,
  "6":0,
  "7":0,
  "8":0,
  "9":1
 },
 "3k_rounds_total":{
  "0":0,
  "1":0,
  "2":2,
  "3":2,
  "4":1,
  "5":0,
  "6":0,
  "7":2,
  "8":1,
  "9":1
 },
 "mvps":{
  "0":1,
  "1":4,
  "2":5,
  "3":3,
  "4":3,
  "5":1,
  "6":0,
  "7":5,
  "8":4,
  "9":4
 },
 "tick":{
  "0":269156,
  "1":269156,
  "2":269156,
  "3":269156,
  "4":269156,
  "5":269156,
  "6":269156,
  "7":269156,
  "8":269156,
  "9":269156
 },
 "steamid":{
  "0":76561198052546265,
  "1":76561198053126645,
  "2":76561198073117127,
  "3":76561198057282432,
  "4":76561197996678278,
  "5":76561198160709585,
  "6":76561198083485506,
  "7":76561197967432889,
  "8":76561198812513923,
  "9":76561198044118796
 },
 "name":{
  "0":"Calyx",
  "1":"NertZ",
  "2":"nicoodoz",
  "3":"kyxsan",
  "4":"TeSeS",
  "5":"sjuush",
  "6":"woxic",
  "7":"MAJ3R",
  "8":"Wicadia",
  "9":"XANTARES"
 }
}